bumpemu/__init__.py
bumpemu/circular_bytearray.py
bumpemu/debug.py
bumpemu/main.py
bumpemu/util.py
bumpemu/charger/__init__.py
bumpemu/charger/options.py
bumpemu/charger/powerlab.py
bumpemu/charger/preset.py
bumpemu/charger/status.py
bumpemu/charger/tester.py
bumpemu/config/presets.yml
bumpemu/controller/__init__.py
bumpemu/controller/bluez_dbus.py
bumpemu/controller/constants.py
bumpemu/controller/emulator.py
bumpemu/controller/message_handler.py
bumpemu/controller/serialize.py
bumpemu/controller/messages/__init__.py
bumpemu/controller/messages/battery.py
bumpemu/controller/messages/bump_settings.py
bumpemu/controller/messages/charger_idle.py
bumpemu/controller/messages/charger_settings.py
bumpemu/controller/messages/charger_status.py
bumpemu/controller/messages/manual_start.py
bumpemu/controller/state_machine/__init__.py
bumpemu/controller/state_machine/event.py
bumpemu/controller/state_machine/state.py
bumpemu-0.0.8.dist-info/LICENSE
bumpemu-0.0.8.dist-info/METADATA
bumpemu-0.0.8.dist-info/WHEEL
bumpemu-0.0.8.dist-info/entry_points.txt
bumpemu-0.0.8.dist-info/top_level.txt
bumpemu-0.0.8.dist-info/RECORD
