Metadata-Version: 2.1
Name: bumpemu
Version: 0.0.8
Summary: A bump controller emulator on Raspberry Pi Zero W.
Home-page: https://github.com/fhriley/bumpemu
Author: Frank Riley
Author-email: fhriley@gmail.com
License: GNU GPLv3
Platform: UNKNOWN
Classifier: Development Status :: 4 - Beta
Classifier: Environment :: Console
Classifier: License :: OSI Approved :: GNU General Public License v3 or later (GPLv3+)
Classifier: Operating System :: POSIX :: Linux
Classifier: Programming Language :: Python :: 3 :: Only
Requires-Python: >=3.5
Requires-Dist: dbus-python (>=1.2.8)
Requires-Dist: PyGObject (>=3.22.0)
Requires-Dist: pyserial (>=3.4)
Requires-Dist: PyYAML (>=3.13)
